llm_release_notes/__init__.py
llm_release_notes/generator.py
llm_release_notes-1.0.1.dist-info/METADATA
llm_release_notes-1.0.1.dist-info/WHEEL
llm_release_notes-1.0.1.dist-info/entry_points.txt
llm_release_notes-1.0.1.dist-info/top_level.txt
llm_release_notes-1.0.1.dist-info/RECORD
